romer_midibot/MPU.py
romer_midibot/__init__.py
romer_midibot/default_configs.py
romer_midibot/midibot.py
romer_midibot/sensors.py
romer_midibot/serial_comm.py
romer_midibot/socket_comm.py
romer_midibot-1.1.5.dist-info/LICENSE
romer_midibot-1.1.5.dist-info/METADATA
romer_midibot-1.1.5.dist-info/WHEEL
romer_midibot-1.1.5.dist-info/top_level.txt
romer_midibot-1.1.5.dist-info/RECORD
