Metadata-Version: 2.1
Name: romer-midibot
Version: 1.1.5
Summary: A Python API for Romer's MIDIbot
Author: Omar Habib
Author-email: omar1farouk@gmail.com
License: Apache License 2.0
Classifier: Programming Language :: Python :: 3
Classifier: License :: OSI Approved :: Apache Software License
Requires-Python: >=3.6
License-File: LICENSE
Requires-Dist: pyserial
